pyparsesynt/__init__.py
pyparsesynt/parser.py
pyparsesynt/repr.py
pyparsesynt/rule.py
pyparsesynt/syn.py
pyparsesynt/token.py
pyparsesynt/writer.py
pyparsesynt-0.0.1.dist-info/LICENSE.md
pyparsesynt-0.0.1.dist-info/METADATA
pyparsesynt-0.0.1.dist-info/WHEEL
pyparsesynt-0.0.1.dist-info/top_level.txt
pyparsesynt-0.0.1.dist-info/RECORD
