Metadata-Version: 2.1
Name: pyparsesynt
Version: 0.0.1
Summary: pyparsesynt - parser for creating syntax tree
Home-page: https://github.com/kr-g/pyparsesynt
Author: k.r. goger
Author-email: k.r.goger+pyparsesynt@gmail.com
License: UNKNOWN
Keywords: compiler construction parser syntax tree
Platform: UNKNOWN
Classifier: Development Status :: 3 - Alpha
Classifier: Operating System :: POSIX :: Linux
Classifier: Intended Audience :: Developers
Classifier: Programming Language :: Python :: 3
Classifier: License :: OSI Approved :: GNU Affero General Public License v3 or later (AGPLv3+)
Requires-Python: >=3.8
